magic_assistant/__init__.py
magic_assistant/action/__init__.py
magic_assistant/action/action.py
magic_assistant/action/action_to_str.py
magic_assistant/action/generative_action.py
magic_assistant/agent/__init__.py
magic_assistant/agent/agent_factory.py
magic_assistant/agent/agent_manager.py
magic_assistant/agent/base_agent.py
magic_assistant/agent/chat/__init__.py
magic_assistant/agent/chat/chat_agent.py
magic_assistant/agent/chat/prompt.py
magic_assistant/agent/execute_cmd/__init__.py
magic_assistant/agent/execute_cmd/execute_cmd_agent.py
magic_assistant/agent/execute_cmd/prompt.py
magic_assistant/agent/plan/__init__.py
magic_assistant/agent/plan/logic.txt
magic_assistant/agent/plan/plan.py
magic_assistant/agent/plan/plan_agent.py
magic_assistant/agent/plan/prompt_tips.py
magic_assistant/agent/plan/sub_agents/__init__.py
magic_assistant/agent/plan/sub_agents/evaluate_result/__init__.py
magic_assistant/agent/plan/sub_agents/evaluate_result/evaluate_result_agent.py
magic_assistant/agent/plan/sub_agents/evaluate_result/prompt.py
magic_assistant/agent/plan/sub_agents/execute_action/__init__.py
magic_assistant/agent/plan/sub_agents/execute_action/execute_action_agent.py
magic_assistant/agent/plan/sub_agents/execute_action/prompt.py
magic_assistant/agent/plan/sub_agents/make_plan/__init__.py
magic_assistant/agent/plan/sub_agents/make_plan/make_plan_agent.py
magic_assistant/agent/plan/sub_agents/make_plan/prompt.py
magic_assistant/agent/role.py
magic_assistant/agent/role_play/README.md
magic_assistant/agent/role_play/agent_react.py
magic_assistant/agent/role_play/prompt.py
magic_assistant/agent/role_play/role_play_agent.py
magic_assistant/chain/__init__.py
magic_assistant/chain/chain.py
magic_assistant/chain/module.py
magic_assistant/cli.py
magic_assistant/config/__init__.py
magic_assistant/config/agent_config.py
magic_assistant/config/global_config.py
magic_assistant/config/misc_config.py
magic_assistant/config/model_config.py
magic_assistant/config/postgre_config.py
magic_assistant-0.0.1.dist-info/LICENSE
magic_assistant-0.0.1.dist-info/METADATA
magic_assistant-0.0.1.dist-info/WHEEL
magic_assistant-0.0.1.dist-info/RECORD
