Metadata-Version: 2.1
Name: magic-assistant
Version: 0.0.1
Summary: An AI agent framework.
Author: luguanglong
Author-email: luguang_long@163.com
Requires-Python: >=3.10,<4.0
Classifier: Programming Language :: Python :: 3
Classifier: Programming Language :: Python :: 3.10
Classifier: Programming Language :: Python :: 3.11
Requires-Dist: accelerate (>=0.21.0,<0.22.0)
Requires-Dist: case-converter (>=1.1.0,<2.0.0)
Requires-Dist: fastapi (>=0.100.0,<0.101.0)
Requires-Dist: llama-cpp-python (>=0.1.68,<0.2.0)
Requires-Dist: loguru (>=0.7.0,<0.8.0)
Requires-Dist: nvidia-cublas-cu11 (==11.10.3.66)
Requires-Dist: pgvector (>=0.2.0,<0.3.0)
Requires-Dist: psycopg2 (>=2.9.7,<3.0.0)
Requires-Dist: pyyaml (>=6.0,<7.0)
Requires-Dist: rich (>=13.5.2,<14.0.0)
Requires-Dist: sentence-transformers (>=2.2.2,<3.0.0)
Requires-Dist: sqlalchemy (>=2.0.19,<3.0.0)
Requires-Dist: sqlalchemy-utils (>=0.41.1,<0.42.0)
Requires-Dist: torch (>=2.0.1,<3.0.0)
Requires-Dist: transformers (>=4.31.0,<5.0.0)
Requires-Dist: uvicorn (>=0.22.0,<0.23.0)
